sanguine/__init__.py
sanguine/__main__.py
sanguine/cli.py
sanguine/constants.py
sanguine/core.py
sanguine/git.py
sanguine/install_uninstall.py
sanguine/meta.py
sanguine/parser.py
sanguine/state.py
sanguine/utils.py
sanguine/assets/ext_to_lang.json
sanguine/assets/prog_langs_schema.json
sanguine/db/__init__.py
sanguine/db/fts.py
sanguine/db/hnsw.py
sanguine-1.2.3.dist-info/licenses/LICENSE
sanguine-1.2.3.dist-info/METADATA
sanguine-1.2.3.dist-info/WHEEL
sanguine-1.2.3.dist-info/entry_points.txt
sanguine-1.2.3.dist-info/top_level.txt
sanguine-1.2.3.dist-info/RECORD
