Metadata-Version: 2.4
Name: sanguine
Version: 1.2.3
Summary: Semantic code indexing tool
Author-email: Nitesh Yadav <nitesh.txt@gmail.com>
License-Expression: MIT
Project-URL: Homepage, https://github.com/n1teshy/sanguine
Project-URL: Repository, https://github.com/n1teshy/sanguine
Project-URL: Issues, https://github.com/n1teshy/sanguine/issues
Classifier: Programming Language :: Python :: 3
Classifier: Operating System :: OS Independent
Requires-Python: >=3.10
License-File: LICENSE
Requires-Dist: peewee
Requires-Dist: tree_sitter_language_pack
Requires-Dist: colorama
Requires-Dist: pathspec
Requires-Dist: tqdm
Requires-Dist: appdirs
Requires-Dist: hnswlib
Requires-Dist: fastembed
Provides-Extra: gpu
Requires-Dist: fastembed-gpu; extra == "gpu"
Dynamic: license-file
